flask_util_job_runner/__init__.py
flask_util_job_runner/api_utils.py
flask_util_job_runner/definitions.py
flask_util_job_runner/flask_utils.py
flask_util_job_runner-0.2.2.dist-info/WHEEL
flask_util_job_runner-0.2.2.dist-info/METADATA
flask_util_job_runner-0.2.2.dist-info/RECORD
