Metadata-Version: 2.1
Name: flask-util-job-runner
Version: 0.2.2
Summary: 
Author: eqqe
Author-email: sfbrey@gmail.com
Requires-Python: >=3.8,<4.0
Classifier: Programming Language :: Python :: 3
Classifier: Programming Language :: Python :: 3.8
Requires-Dist: Flask (==1.1.2)
Requires-Dist: gunicorn (==20.0.4)
Requires-Dist: minio (==6.0.0)
Requires-Dist: redis (==3.5.3)
Requires-Dist: requests (==2.24.0)
